gitgrind/__init__.py
gitgrind/main.py
gitgrind/test_grind.py
gitgrind-0.2.0.dist-info/licenses/LICENSE
gitgrind-0.2.0.dist-info/METADATA
gitgrind-0.2.0.dist-info/WHEEL
gitgrind-0.2.0.dist-info/entry_points.txt
gitgrind-0.2.0.dist-info/top_level.txt
gitgrind-0.2.0.dist-info/RECORD
