Metadata-Version: 2.4
Name: gitgrind
Version: 0.2.0
Summary: find files and commits in multiple repos, stashes, dangling commits.
Author-email: Kurt Godwin <48928663+kurt-cb@users.noreply.github.com>
Maintainer-email: Kurt Godwin <48928663+kurt-cb@users.noreply.github.com>
License: MIT License
Project-URL: Homepage, https://github.com/kurt-cb/gitgrind/
Project-URL: Documentation, https://gitgrind.readthedocs.io/
Project-URL: Repository, https://github.com/kurt-cb/gitgrind
Keywords: python,git,grep,find,dangling,commit,search
Classifier: Programming Language :: Python :: 3
Classifier: License :: OSI Approved :: MIT License
Classifier: Operating System :: OS Independent
Requires-Python: >=3.8
License-File: LICENSE
Requires-Dist: pygit2>=1.18.2
Provides-Extra: dev
Requires-Dist: pytest; extra == "dev"
Requires-Dist: flake8; extra == "dev"
Requires-Dist: black; extra == "dev"
Dynamic: license-file
